{
  "travel_date": "2026-10-03",
  "recommendation": {
    "recommended_cities": [
      "서울",
      "부산",
      "전주"
    ],
    "weather": "10월 초는 가을로 접어드는 시기로, 대체로 맑고 선선한 날씨가 이어집니다. 평균 기온은 15도에서 20도 사이로 쾌적합니다.",
    "events": [
      "서울세계불꽃축제",
      "부산국제영화제",
      "전주한지문화축제"
    ],
    "reason": "서울은 다양한 문화 행사와 볼거리가 많아 여행하기 좋은 도시입니다. 부산은 국제영화제가 열려 세계적인 영화와 문화를 경험할 수 있는 기회입니다. 전주는 전통과 현대가 어우러진 한지문화축제로 한국의 전통문화를 깊이 있게 체험할 수 있는 장소입니다."
  },
  "restaurants_by_city": {
    "서울": [
      {
        "name": "쟝블랑제리",
        "address": "서울 관악구 낙성대역길 8",
        "category": "음식점 > 간식 > 제과,베이커리",
        "url": "http://place.map.kakao.com/16990385",
        "x": 126.961968234363,
        "y": 37.477157623199
      },
      {
        "name": "마포양고기전문점 램랜드",
        "address": "서울 마포구 토정로 255",
        "category": "음식점 > 한식 > 육류,고기",
        "url": "http://place.map.kakao.com/7859798",
        "x": 126.93877507299659,
        "y": 37.54349244061807
      },
      {
        "name": "무교동북어국집",
        "address": "서울 중구 을지로1길 38",
        "category": "음식점 > 한식 > 해장국",
        "url": "http://place.map.kakao.com/11064200",
        "x": 126.9798518336699,
        "y": 37.56773441926809
      },
      {
        "name": "사랑방칼국수",
        "address": "서울 중구 퇴계로27길 46",
        "category": "음식점 > 한식 > 국수 > 칼국수",
        "url": "http://place.map.kakao.com/7919722",
        "x": 126.99133001470943,
        "y": 37.563266879496595
      },
      {
        "name": "원조호수삼계탕 본점",
        "address": "서울 영등포구 도림로 276",
        "category": "음식점 > 한식 > 육류,고기 > 닭요리 > 삼계탕",
        "url": "http://place.map.kakao.com/8510748",
        "x": 126.90434880185744,
        "y": 37.50266588317401
      }
    ],
    "부산": [
      {
        "name": "고옥",
        "address": "부산 수영구 광남로 6",
        "category": "음식점 > 일식 > 일식집",
        "url": "http://place.map.kakao.com/15206679",
        "x": 129.109683336517,
        "y": 35.1436194428048
      },
      {
        "name": "김유순대구뽈찜전문",
        "address": "부산 남구 진남로 15",
        "category": "음식점 > 한식 > 해물,생선",
        "url": "http://place.map.kakao.com/8116757",
        "x": 129.091513709565,
        "y": 35.1363540063858
      },
      {
        "name": "일광당",
        "address": "부산 기장군 일광읍 일광로 125-1",
        "category": "음식점 > 간식",
        "url": "http://place.map.kakao.com/14723726",
        "x": 129.235227867827,
        "y": 35.2665874736785
      },
      {
        "name": "후발대",
        "address": "부산 부산진구 부전로20번길 32-5",
        "category": "음식점 > 한식 > 육류,고기",
        "url": "http://place.map.kakao.com/12030410",
        "x": 129.05704336839048,
        "y": 35.1535238814853
      },
      {
        "name": "중앙곰탕",
        "address": "부산 중구 충장대로9번길 9",
        "category": "음식점 > 한식 > 곰탕",
        "url": "http://place.map.kakao.com/10795079",
        "x": 129.03734668670725,
        "y": 35.106111028005785
      }
    ],
    "전주": [
      {
        "name": "전주왱이콩나물국밥전문점",
        "address": "전북특별자치도 전주시 완산구 동문길 88",
        "category": "음식점 > 한식 > 국밥",
        "url": "http://place.map.kakao.com/26615208",
        "x": 127.14917874864973,
        "y": 35.81828668481779
      },
      {
        "name": "오원집 본점",
        "address": "전북특별자치도 전주시 완산구 공북로 84",
        "category": "음식점 > 한식",
        "url": "http://place.map.kakao.com/8481800",
        "x": 127.14089556470701,
        "y": 35.82609708132779
      },
      {
        "name": "메르밀진미집 본점",
        "address": "전북특별자치도 전주시 완산구 전주천동로 94",
        "category": "음식점 > 한식 > 국수",
        "url": "http://place.map.kakao.com/8600047",
        "x": 127.15041781442807,
        "y": 35.81109758690795
      },
      {
        "name": "금암피순대",
        "address": "전북특별자치도 전주시 덕진구 기린대로 400-61",
        "category": "음식점 > 한식 > 순대",
        "url": "http://place.map.kakao.com/21291721",
        "x": 127.132807456023,
        "y": 35.838370612481
      },
      {
        "name": "백김치새싹막회 우아본점",
        "address": "전북특별자치도 전주시 덕진구 백제대로 790",
        "category": "음식점 > 한식 > 해물,생선 > 회",
        "url": "http://place.map.kakao.com/11608851",
        "x": 127.15495546604821,
        "y": 35.84699345407851
      }
    ]
  },
  "errors": []
}